[{"id":"371","name":"Abel"},{"id":"1","name":"Acheron"},{"id":"2","name":"Alchemyglove"},{"id":"3","name":"Alcor"},{"id":"4","name":"Alioth"},{"id":"5","name":"Alraune"},{"id":"130","name":"Amberbeast"},{"id":"7","name":"Anarchy"},{"id":"694","name":"Ancestralweapon"},{"id":"8","name":"Andromeda"},{"id":"202","name":"Angel"},{"id":"13","name":"Ant"},{"id":"14","name":"Antsquad"},{"id":"16","name":"Aparajita"},{"id":"259","name":"Aphrodite"},{"id":"373","name":"Apollo"},{"id":"112","name":"Apsu"},{"id":"17","name":"Apus"},{"id":"18","name":"Aquarius"},{"id":"20","name":"Aquila"},{"id":"24","name":"Ara"},{"id":"335","name":"Aranea"},{"id":"25","name":"Ares"},{"id":"26","name":"Aries"},{"id":"62","name":"Arliss"},{"id":"28","name":"Arondight"},{"id":"29","name":"Arsmagna"},{"id":"475","name":"Artemis"},{"id":"10","name":"Athanasia"},{"id":"6","name":"Athena"},{"id":"31","name":"Atrium"},{"id":"32","name":"Auriga"},{"id":"381","name":"Aurora"},{"id":"220","name":"Axe"},{"id":"33","name":"Azoth"},{"id":"34","name":"Bacchus"},{"id":"35","name":"Balor"},{"id":"36","name":"Balron"},{"id":"37","name":"Banshee"},{"id":"38","name":"Baphomet"},{"id":"39","name":"Basic"},{"id":"40","name":"Basilisk"},{"id":"41","name":"Bat"},{"id":"42","name":"Beetle"},{"id":"44","name":"Behemoth"},{"id":"45","name":"Benetnasch"},{"id":"46","name":"Bennu"},{"id":"47","name":"Bhuj"},{"id":"48","name":"Blackterror"},{"id":"219","name":"Blackthunder"},{"id":"185","name":"Blueflame"},{"id":"460","name":"Bluegod"},{"id":"399","name":"Bluewarrior"},{"id":"49","name":"Bootes"},{"id":"50","name":"Brionac"},{"id":"52","name":"Caelum"},{"id":"53","name":"Caitsith"},{"id":"54","name":"Camelopardalis"},{"id":"55","name":"Cancer"},{"id":"57","name":"Canesvenatici"},{"id":"58","name":"Canismajor"},{"id":"409","name":"Canisminor"},{"id":"59","name":"Capricorn"},{"id":"61","name":"Carina"},{"id":"348","name":"Carnelianonyx"},{"id":"63","name":"Cassiopeia"},{"id":"64","name":"Centaurus"},{"id":"65","name":"Cepheus"},{"id":"66","name":"Cerberus"},{"id":"67","name":"Cetus"},{"id":"70","name":"Chamaeleon"},{"id":"71","name":"Cherub"},{"id":"72","name":"Chrysaor"},{"id":"73","name":"Circinus"},{"id":"401","name":"Clarent"},{"id":"77","name":"Columba"},{"id":"78","name":"Comaberenice"},{"id":"79","name":"Coronaaustralis"},{"id":"80","name":"Coronaborealis"},{"id":"82","name":"Corvus"},{"id":"83","name":"Crater"},{"id":"283","name":"Crimsonlava"},{"id":"177","name":"Crossbow"},{"id":"86","name":"Crux"},{"id":"87","name":"Crystal"},{"id":"89","name":"Cyclops"},{"id":"90","name":"Cygnus"},{"id":"95","name":"Daggers"},{"id":"457","name":"Darkgod"},{"id":"395","name":"Dawon"},{"id":"97","name":"Deadlybeetle"},{"id":"98","name":"Deadlyharlequin"},{"id":"101","name":"Deathwatch"},{"id":"462","name":"Deception"},{"id":"102","name":"Deep"},{"id":"105","name":"Delphinus"},{"id":"162","name":"Demonimpact"},{"id":"452","name":"Desert"},{"id":"329","name":"Destruction"},{"id":"107","name":"Diana"},{"id":"600","name":"Dolphin"},{"id":"425","name":"Dorado"},{"id":"111","name":"Draco"},{"id":"81","name":"Dracodent"},{"id":"120","name":"Drbal"},{"id":"121","name":"Dryad"},{"id":"122","name":"Dubhe"},{"id":"123","name":"Duel"},{"id":"124","name":"Dullahan"},{"id":"125","name":"Durandal"},{"id":"128","name":"Eikthyrnir"},{"id":"129","name":"Electricity"},{"id":"131","name":"Elf"},{"id":"244","name":"Empress"},{"id":"113","name":"Enki"},{"id":"133","name":"Equuleus"},{"id":"135","name":"Eridanus"},{"id":"136","name":"Eris"},{"id":"400","name":"Excalibur"},{"id":"229","name":"Falchion"},{"id":"171","name":"Famine"},{"id":"407","name":"Fear"},{"id":"109","name":"Flamberge"},{"id":"84","name":"Flame"},{"id":"138","name":"Flamingfist"},{"id":"139","name":"Fornax"},{"id":"140","name":"Frey"},{"id":"141","name":"Frog"},{"id":"477","name":"Galanthus"},{"id":"144","name":"Gargoyle"},{"id":"145","name":"Garmr"},{"id":"146","name":"Garuda"},{"id":"148","name":"Gemini"},{"id":"150","name":"Genbu"},{"id":"328","name":"Genesis"},{"id":"151","name":"Ghostsmaster"},{"id":"152","name":"Golem"},{"id":"153","name":"Gorgon"},{"id":"154","name":"Gram"},{"id":"155","name":"Grani"},{"id":"330","name":"Graviton"},{"id":"11","name":"Grazia"},{"id":"274","name":"Greyblade"},{"id":"156","name":"Griffon"},{"id":"157","name":"Grus"},{"id":"158","name":"Gullinbursti"},{"id":"126","name":"Gurthang"},{"id":"159","name":"Hades"},{"id":"160","name":"Hakuryu"},{"id":"161","name":"Hakutaku"},{"id":"163","name":"Hanuman"},{"id":"451","name":"Harmony"},{"id":"164","name":"Harpy"},{"id":"165","name":"Heracles"},{"id":"167","name":"Hornet"},{"id":"168","name":"Horologium"},{"id":"169","name":"Hraesvelgr"},{"id":"172","name":"Hydra"},{"id":"173","name":"Hydrus"},{"id":"174","name":"Hypnos"},{"id":"176","name":"Icelus"},{"id":"178","name":"Illusions"},{"id":"76","name":"Impulsemace"},{"id":"179","name":"Indus"},{"id":"240","name":"Jadearmor"},{"id":"180","name":"Jamadhar"},{"id":"181","name":"Jellyfish"},{"id":"247","name":"Kalfu"},{"id":"233","name":"Katar"},{"id":"479","name":"Kelpie"},{"id":"182","name":"Ker"},{"id":"183","name":"Kohinoor"},{"id":"184","name":"Kraken"},{"id":"368","name":"Kusanagi"},{"id":"186","name":"Lacerta"},{"id":"478","name":"Laelaps"},{"id":"187","name":"Land"},{"id":"51","name":"Lapislazuli"},{"id":"189","name":"Leo"},{"id":"191","name":"Leominor"},{"id":"195","name":"Lepus"},{"id":"197","name":"Libra"},{"id":"463","name":"Lies"},{"id":"199","name":"Loki"},{"id":"201","name":"Lotus"},{"id":"250","name":"Loupblanc"},{"id":"204","name":"Lupus"},{"id":"206","name":"Lycaon"},{"id":"110","name":"Lynx"},{"id":"207","name":"Lyra"},{"id":"132","name":"Lyumnades"},{"id":"209","name":"Madness"},{"id":"342","name":"Malachite"},{"id":"210","name":"Malice"},{"id":"211","name":"Mandrake"},{"id":"212","name":"Mantis"},{"id":"214","name":"Marine"},{"id":"127","name":"Mariner"},{"id":"216","name":"Mars"},{"id":"217","name":"Martiancommander"},{"id":"464","name":"Massacre"},{"id":"74","name":"Maxbrilliants"},{"id":"343","name":"Megasdepranon"},{"id":"218","name":"Megrez"},{"id":"221","name":"Mensa"},{"id":"222","name":"Mephistopheles"},{"id":"223","name":"Merak"},{"id":"224","name":"Mermaid"},{"id":"225","name":"Midgard"},{"id":"226","name":"Minotaur"},{"id":"227","name":"Mizar"},{"id":"228","name":"Monoceros"},{"id":"810","name":"Moros"},{"id":"232","name":"Morpheus"},{"id":"234","name":"Murder"},{"id":"235","name":"Musca"},{"id":"85","name":"Musica"},{"id":"236","name":"Mysticstone"},{"id":"238","name":"Nasu"},{"id":"239","name":"Necromancer"},{"id":"115","name":"Nemesis"},{"id":"237","name":"Nidhoggr"},{"id":"241","name":"Ninetailedfox"},{"id":"166","name":"Noctua"},{"id":"243","name":"Norma"},{"id":"397","name":"Nothing"},{"id":"403","name":"Oath"},{"id":"245","name":"Oblivion"},{"id":"246","name":"Odin"},{"id":"248","name":"Oneiros"},{"id":"327","name":"Onyx"},{"id":"170","name":"Opal"},{"id":"249","name":"Ophiuchus"},{"id":"252","name":"Orion"},{"id":"242","name":"Owl"},{"id":"255","name":"Pain"},{"id":"256","name":"Pallas"},{"id":"398","name":"Pallasites"},{"id":"257","name":"Papillon"},{"id":"258","name":"Pavo"},{"id":"213","name":"Pearldragon"},{"id":"261","name":"Pegasus"},{"id":"142","name":"Perfectpawn"},{"id":"272","name":"Persephone"},{"id":"273","name":"Perseus"},{"id":"476","name":"Phaeton"},{"id":"275","name":"Phantasos"},{"id":"147","name":"Phantomarm"},{"id":"449","name":"Phantomarmofhyperion"},{"id":"276","name":"Phecda"},{"id":"277","name":"Phobetor"},{"id":"278","name":"Phoenix"},{"id":"331","name":"Photon"},{"id":"284","name":"Pisces"},{"id":"286","name":"Piscisaustrinus"},{"id":"465","name":"Plunder"},{"id":"287","name":"Polaris"},{"id":"21","name":"Poseidon"},{"id":"289","name":"Punishment"},{"id":"290","name":"Puppis"},{"id":"292","name":"Pyxis"},{"id":"294","name":"Quetzalcoatl"},{"id":"295","name":"Rangifer"},{"id":"96","name":"Rapier"},{"id":"461","name":"Redgod"},{"id":"296","name":"Reticulum"},{"id":"297","name":"Revenge"},{"id":"298","name":"Romulus"},{"id":"15","name":"Rubyiron"},{"id":"279","name":"Ruin"},{"id":"300","name":"Rung"},{"id":"301","name":"Sagitta"},{"id":"302","name":"Sagittarius"},{"id":"304","name":"Saturn"},{"id":"326","name":"Scarletjanus"},{"id":"305","name":"Scorpio"},{"id":"307","name":"Scutum"},{"id":"137","name":"Scylla"},{"id":"606","name":"Sea"},{"id":"309","name":"Seadragon"},{"id":"175","name":"Seahorse"},{"id":"311","name":"Seaserpent"},{"id":"312","name":"Seraph"},{"id":"253","name":"Serket"},{"id":"313","name":"Serpens"},{"id":"314","name":"Sextans"},{"id":"315","name":"Shadow"},{"id":"143","name":"Shamshir"},{"id":"251","name":"Silveroriolus"},{"id":"103","name":"Siren"},{"id":"317","name":"Skeleton"},{"id":"318","name":"Sky"},{"id":"69","name":"Slashreaper"},{"id":"319","name":"Sledgehammer"},{"id":"321","name":"Slicedblood"},{"id":"364","name":"Snakeplasma"},{"id":"322","name":"Soldier"},{"id":"99","name":"Soulkiller"},{"id":"323","name":"Sparrow"},{"id":"324","name":"Sphinx"},{"id":"325","name":"Spider"},{"id":"231","name":"Starcrusher"},{"id":"333","name":"Starruby"},{"id":"106","name":"Starsapphire"},{"id":"427","name":"Super"},{"id":"268","name":"Supremesynapse"},{"id":"332","name":"Sylph"},{"id":"88","name":"Tanken"},{"id":"334","name":"Tanngrisnir"},{"id":"336","name":"Taurus"},{"id":"408","name":"Terror"},{"id":"338","name":"Tezcatlipoca"},{"id":"339","name":"Thanatos"},{"id":"91","name":"Thatanka"},{"id":"341","name":"Thrones"},{"id":"453","name":"Thunderstorm"},{"id":"363","name":"Topaz"},{"id":"434","name":"Tornado"},{"id":"344","name":"Triangulum"},{"id":"345","name":"Triplerod"},{"id":"435","name":"Triton"},{"id":"346","name":"Troll"},{"id":"454","name":"Tsunami"},{"id":"347","name":"Tucana"},{"id":"349","name":"Ullr"},{"id":"350","name":"Upyr"},{"id":"351","name":"Ursamajor"},{"id":"352","name":"Ursaminor"},{"id":"353","name":"Valkyrie"},{"id":"203","name":"Valravn"},{"id":"354","name":"Vampire"},{"id":"355","name":"Vela"},{"id":"356","name":"Virgo"},{"id":"358","name":"Virtues"},{"id":"359","name":"Volans"},{"id":"360","name":"Vorpal"},{"id":"361","name":"Vuivre"},{"id":"362","name":"Vulcanus"},{"id":"192","name":"Walkyrie"},{"id":"196","name":"Whitewind"},{"id":"365","name":"Worm"},{"id":"230","name":"Wyrm"},{"id":"9","name":"Wyvern"},{"id":"108","name":"Xiphos"},{"id":"367","name":"Youaltepuztli"},{"id":"436","name":"Zeus"},{"id":"12","name":"Ngalyod"},{"id":"19","name":""},{"id":"22","name":""},{"id":"23","name":""},{"id":"27","name":""},{"id":"30","name":""},{"id":"43","name":""},{"id":"56","name":""},{"id":"60","name":""},{"id":"68","name":""},{"id":"75","name":""},{"id":"92","name":""},{"id":"93","name":""},{"id":"94","name":""},{"id":"100","name":""},{"id":"104","name":""},{"id":"114","name":""},{"id":"116","name":""},{"id":"117","name":""},{"id":"118","name":""},{"id":"119","name":""},{"id":"134","name":""},{"id":"149","name":""},{"id":"188","name":""},{"id":"190","name":""},{"id":"193","name":""},{"id":"194","name":""},{"id":"198","name":""},{"id":"200","name":""},{"id":"205","name":""},{"id":"208","name":""},{"id":"215","name":""},{"id":"254","name":""},{"id":"260","name":""},{"id":"262","name":""},{"id":"263","name":""},{"id":"264","name":""},{"id":"265","name":""},{"id":"266","name":""},{"id":"267","name":""},{"id":"269","name":""},{"id":"270","name":""},{"id":"271","name":""},{"id":"280","name":""},{"id":"281","name":""},{"id":"282","name":""},{"id":"285","name":""},{"id":"288","name":""},{"id":"291","name":""},{"id":"293","name":""},{"id":"299","name":""},{"id":"303","name":""},{"id":"306","name":""},{"id":"308","name":""},{"id":"310","name":""},{"id":"316","name":""},{"id":"320","name":""},{"id":"337","name":""},{"id":"340","name":""},{"id":"357","name":""},{"id":"366","name":""},{"id":"369","name":""},{"id":"370","name":""},{"id":"372","name":""},{"id":"374","name":""},{"id":"375","name":""},{"id":"376","name":""},{"id":"377","name":""},{"id":"378","name":""},{"id":"379","name":""},{"id":"380","name":""},{"id":"382","name":""},{"id":"383","name":""},{"id":"384","name":""},{"id":"385","name":""},{"id":"386","name":""},{"id":"387","name":""},{"id":"388","name":""},{"id":"389","name":""},{"id":"390","name":""},{"id":"391","name":""},{"id":"392","name":""},{"id":"393","name":""},{"id":"394","name":""},{"id":"396","name":""},{"id":"402","name":""},{"id":"404","name":""},{"id":"405","name":""},{"id":"406","name":""},{"id":"410","name":""},{"id":"411","name":""},{"id":"412","name":""},{"id":"413","name":""},{"id":"414","name":""},{"id":"415","name":""},{"id":"416","name":""},{"id":"417","name":""},{"id":"418","name":""},{"id":"419","name":""},{"id":"420","name":""},{"id":"421","name":""},{"id":"422","name":""},{"id":"423","name":""},{"id":"424","name":""},{"id":"426","name":""},{"id":"428","name":""},{"id":"429","name":""},{"id":"430","name":""},{"id":"431","name":""},{"id":"432","name":""},{"id":"433","name":""},{"id":"437","name":""},{"id":"438","name":""},{"id":"439","name":""},{"id":"440","name":""},{"id":"441","name":""},{"id":"442","name":""},{"id":"443","name":""},{"id":"444","name":""},{"id":"445","name":""},{"id":"446","name":""},{"id":"447","name":""},{"id":"448","name":""},{"id":"450","name":""},{"id":"455","name":""},{"id":"456","name":""},{"id":"458","name":""},{"id":"459","name":""},{"id":"466","name":""},{"id":"467","name":""},{"id":"468","name":""},{"id":"469","name":""},{"id":"470","name":""},{"id":"471","name":""},{"id":"472","name":""},{"id":"473","name":""},{"id":"474","name":""},{"id":"480","name":""},{"id":"481","name":""},{"id":"482","name":""},{"id":"483","name":""},{"id":"484","name":""},{"id":"485","name":""},{"id":"486","name":""},{"id":"487","name":""},{"id":"488","name":""},{"id":"489","name":""},{"id":"490","name":""},{"id":"491","name":""},{"id":"492","name":""},{"id":"493","name":""},{"id":"494","name":""},{"id":"495","name":""},{"id":"496","name":""},{"id":"497","name":""},{"id":"498","name":""},{"id":"499","name":""},{"id":"500","name":""},{"id":"501","name":""},{"id":"502","name":""},{"id":"503","name":""},{"id":"504","name":""},{"id":"505","name":""},{"id":"506","name":""},{"id":"507","name":""},{"id":"508","name":""},{"id":"509","name":""},{"id":"510","name":""},{"id":"511","name":""},{"id":"512","name":""},{"id":"513","name":""},{"id":"514","name":""},{"id":"515","name":""},{"id":"516","name":""},{"id":"517","name":""},{"id":"518","name":""},{"id":"519","name":""},{"id":"520","name":""},{"id":"521","name":""},{"id":"522","name":""},{"id":"523","name":""},{"id":"524","name":""},{"id":"525","name":""},{"id":"526","name":""},{"id":"527","name":""},{"id":"528","name":""},{"id":"529","name":""},{"id":"530","name":""},{"id":"531","name":""},{"id":"532","name":""},{"id":"533","name":""},{"id":"534","name":""},{"id":"535","name":""},{"id":"536","name":""},{"id":"537","name":""},{"id":"538","name":""},{"id":"539","name":""},{"id":"540","name":""},{"id":"541","name":""},{"id":"542","name":""},{"id":"543","name":""},{"id":"544","name":""},{"id":"545","name":""},{"id":"546","name":""},{"id":"547","name":""},{"id":"548","name":""},{"id":"549","name":""},{"id":"550","name":""},{"id":"551","name":""},{"id":"552","name":""},{"id":"553","name":""},{"id":"554","name":""},{"id":"555","name":""},{"id":"556","name":""},{"id":"557","name":""},{"id":"558","name":""},{"id":"559","name":""},{"id":"560","name":""},{"id":"561","name":""},{"id":"562","name":""},{"id":"563","name":""},{"id":"564","name":""},{"id":"565","name":""},{"id":"566","name":""},{"id":"567","name":""},{"id":"568","name":""},{"id":"569","name":""},{"id":"570","name":""},{"id":"571","name":""},{"id":"572","name":""},{"id":"573","name":""},{"id":"574","name":""},{"id":"575","name":""},{"id":"576","name":""},{"id":"577","name":""},{"id":"578","name":""},{"id":"579","name":""},{"id":"580","name":""},{"id":"581","name":""},{"id":"582","name":""},{"id":"583","name":""},{"id":"584","name":""},{"id":"585","name":""},{"id":"586","name":""},{"id":"587","name":""},{"id":"588","name":""},{"id":"589","name":""},{"id":"590","name":""},{"id":"591","name":""},{"id":"592","name":""},{"id":"593","name":""},{"id":"594","name":""},{"id":"595","name":""},{"id":"596","name":""},{"id":"597","name":""},{"id":"598","name":""},{"id":"599","name":""},{"id":"601","name":""},{"id":"602","name":""},{"id":"603","name":""},{"id":"604","name":""},{"id":"605","name":""},{"id":"607","name":""},{"id":"608","name":""},{"id":"609","name":""},{"id":"610","name":""},{"id":"611","name":""},{"id":"612","name":""},{"id":"613","name":""},{"id":"614","name":""},{"id":"615","name":""},{"id":"616","name":""},{"id":"617","name":""},{"id":"618","name":""},{"id":"619","name":""},{"id":"620","name":""},{"id":"621","name":""},{"id":"622","name":""},{"id":"623","name":""},{"id":"624","name":""},{"id":"625","name":""},{"id":"626","name":""},{"id":"627","name":""},{"id":"628","name":""},{"id":"629","name":""},{"id":"630","name":""},{"id":"631","name":""},{"id":"632","name":""},{"id":"633","name":""},{"id":"634","name":""},{"id":"635","name":""},{"id":"636","name":""},{"id":"637","name":""},{"id":"638","name":""},{"id":"639","name":""},{"id":"640","name":""},{"id":"641","name":""},{"id":"642","name":""},{"id":"643","name":""},{"id":"644","name":""},{"id":"645","name":""},{"id":"646","name":""},{"id":"647","name":""},{"id":"648","name":""},{"id":"649","name":""},{"id":"650","name":""},{"id":"651","name":""},{"id":"652","name":""},{"id":"653","name":""},{"id":"654","name":""},{"id":"655","name":""},{"id":"656","name":""},{"id":"657","name":""},{"id":"658","name":""},{"id":"659","name":""},{"id":"660","name":""},{"id":"661","name":""},{"id":"662","name":""},{"id":"663","name":""},{"id":"664","name":""},{"id":"665","name":""},{"id":"666","name":""},{"id":"667","name":""},{"id":"668","name":""},{"id":"669","name":""},{"id":"670","name":""},{"id":"671","name":""},{"id":"672","name":""},{"id":"673","name":""},{"id":"674","name":""},{"id":"675","name":""},{"id":"676","name":""},{"id":"677","name":""},{"id":"678","name":""},{"id":"679","name":""},{"id":"680","name":""},{"id":"681","name":""},{"id":"682","name":""},{"id":"683","name":""},{"id":"684","name":""},{"id":"685","name":""},{"id":"686","name":""},{"id":"687","name":""},{"id":"688","name":""},{"id":"689","name":""},{"id":"690","name":""},{"id":"691","name":""},{"id":"692","name":""},{"id":"693","name":""},{"id":"695","name":""},{"id":"696","name":""},{"id":"697","name":""},{"id":"698","name":""},{"id":"699","name":""},{"id":"700","name":""},{"id":"701","name":""},{"id":"702","name":""},{"id":"703","name":""},{"id":"704","name":""},{"id":"705","name":""},{"id":"706","name":""},{"id":"707","name":""},{"id":"708","name":""},{"id":"709","name":""},{"id":"710","name":""},{"id":"711","name":""},{"id":"712","name":""},{"id":"713","name":""},{"id":"714","name":""},{"id":"715","name":""},{"id":"716","name":""},{"id":"717","name":""},{"id":"718","name":""},{"id":"719","name":""},{"id":"720","name":""},{"id":"721","name":""},{"id":"722","name":""},{"id":"723","name":""},{"id":"724","name":""},{"id":"725","name":""},{"id":"726","name":""},{"id":"727","name":""},{"id":"728","name":""},{"id":"729","name":""},{"id":"730","name":""},{"id":"731","name":""},{"id":"732","name":""},{"id":"733","name":""},{"id":"734","name":""},{"id":"735","name":""},{"id":"736","name":""},{"id":"737","name":""},{"id":"738","name":""},{"id":"739","name":""},{"id":"740","name":""},{"id":"741","name":""},{"id":"742","name":""},{"id":"743","name":""},{"id":"744","name":""},{"id":"745","name":""},{"id":"746","name":""},{"id":"747","name":""},{"id":"748","name":""},{"id":"749","name":""},{"id":"750","name":""},{"id":"751","name":""},{"id":"752","name":""},{"id":"753","name":""},{"id":"754","name":""},{"id":"755","name":""},{"id":"756","name":""},{"id":"757","name":""},{"id":"758","name":""},{"id":"759","name":""},{"id":"760","name":""},{"id":"761","name":""},{"id":"762","name":""},{"id":"763","name":""},{"id":"764","name":""},{"id":"765","name":""},{"id":"766","name":""},{"id":"767","name":""},{"id":"768","name":""},{"id":"769","name":""},{"id":"770","name":""},{"id":"771","name":""},{"id":"772","name":""},{"id":"773","name":""},{"id":"774","name":""},{"id":"775","name":""},{"id":"776","name":""},{"id":"777","name":""},{"id":"778","name":""},{"id":"779","name":""},{"id":"780","name":""},{"id":"781","name":""},{"id":"782","name":""},{"id":"783","name":""},{"id":"784","name":""},{"id":"785","name":""},{"id":"786","name":""},{"id":"787","name":""},{"id":"788","name":""},{"id":"789","name":""},{"id":"790","name":""},{"id":"791","name":""},{"id":"792","name":""},{"id":"793","name":""},{"id":"794","name":""},{"id":"795","name":""},{"id":"796","name":""},{"id":"797","name":""},{"id":"798","name":""},{"id":"799","name":""},{"id":"800","name":""},{"id":"801","name":""},{"id":"802","name":""},{"id":"803","name":""},{"id":"804","name":""},{"id":"805","name":""},{"id":"806","name":""},{"id":"807","name":""},{"id":"808","name":""},{"id":"809","name":""}]